models/__init__.py
models/robot.py
tests/__init__.py
tests/conftest.py
tests/test_core/__init__.py
tests/test_core/mock_node.py
tests/test_core/test_node.py
tests/test_core/test_utils.py
tests/test_integration/__init__.py
tests/test_integration/test_messaging.py
tests/test_models/__init__.py
tests/test_models/test_common.py
tests/test_models/test_robot.py
tests/test_models/test_serialization.py
tide/__init__.py
tide/cli.py
tide/namespaces.py
tide/bt/__init__.py
tide/bt/core.py
tide/cli/__init__.py
tide/cli/main.py
tide/cli/utils.py
tide/cli/commands/__init__.py
tide/cli/commands/init.py
tide/cli/commands/init_config.py
tide/cli/commands/init_pingpong.py
tide/cli/commands/status.py
tide/cli/commands/up.py
tide/cli/templates/README.md.template
tide/cli/templates/hello_world_node.py.template
tide/cli/templates/main.py.template
tide/cli/templates/requirements.txt.template
tide/cli/templates/config/config.yaml.template
tide/cli/templates/nodes/monitor_node.py.template
tide/cli/templates/nodes/ping_node.py.template
tide/cli/templates/nodes/pong_node.py.template
tide/cli/templates/nodes/robot_node.py.template
tide/cli/templates/nodes/teleop_node.py.template
tide/components/__init__.py
tide/components/behavior_tree_node.py
tide/components/mux_node.py
tide/components/pid_node.py
tide/components/pose_estimator.py
tide/components/rerun_node.py
tide/components/webcam_node.py
tide/config/__init__.py
tide/core/__init__.py
tide/core/node.py
tide/core/utils.py
tide/core/geometry/__init__.py
tide/examples/simple_robot.py
tide/models/__init__.py
tide/models/common.py
tide/models/robot.py
tide/models/serialization.py
tide_sdk-0.1.13.dist-info/METADATA
tide_sdk-0.1.13.dist-info/WHEEL
tide_sdk-0.1.13.dist-info/entry_points.txt
tide_sdk-0.1.13.dist-info/top_level.txt
tide_sdk-0.1.13.dist-info/RECORD
