Metadata-Version: 2.4
Name: tide-sdk
Version: 0.1.13
Summary: A Zenoh-based robotics framework with opinionated namespacing
Author: Tide Team
Requires-Python: >=3.12
Requires-Dist: cbor2>=5.6.5
Requires-Dist: eclipse-zenoh>=1.3.4
Requires-Dist: hypothesis>=6.131.15
Requires-Dist: numpy>=2.2.6
Requires-Dist: opencv-python>=4.12.0.88
Requires-Dist: pydantic>=2.0.0
Requires-Dist: pytest>=8.3.5
Requires-Dist: pytest-cov>=6.1.1
Requires-Dist: pyyaml>=6.0
Requires-Dist: rerun-sdk>=0.23.4
Requires-Dist: rich>=13.6.0
Dynamic: author
Dynamic: requires-python
